certobs/CERT-Cat.dat
certobs/__init__.py
certobs/ajuste.py
certobs/fit.py
certobs/grid_otf.py
certobs/healpix.py
certobs/hmsdec.py
certobs/otf.py
certobs/plot.py
certobs/__pycache__/__init__.cpython-36.pyc
certobs/__pycache__/__init__.cpython-37.pyc
certobs/obs2014-04-04/scan-2014-04-04.topo
certobs/obs2014-04-04/scan-2019-09-24 15:02:08.524941.topo
certobs/obs2014-04-04/tip-az180.00002014-04-04.topo
certobs/obs2014-04-04/tip-az1802014-04-04.topo
certobs/obs2014-04-04/track-mars2014-04-04.topo
certobs/obs2014-04-04/transit-mars2014-04-04.topo
certobs/obs2019-09-24/TIP1.topo
certobs/obs2019-09-24/track-CasA---2019-09-24.topo
certobs/obs2019-09-25/tip-az2019.09.25-12.00.topo
certobs/obs2019-09-25/tip-az2019.09.25-12.20.topo
certobs/obs2019-09-25/tip-az2019.09.25-12.40.topo
certobs/obs2019-09-25/tip-az2019.09.25-13.00.topo
certobs/obs2019-09-25/tip-az2019.09.25-13.20.topo
certobs/obs2019-09-25/tip-az2019.09.25-13.40.topo
certobs/obs2019-09-25/tip-az2019.09.25-14.00.topo
certobs/obs2019-09-25/tip-az2019.09.25-14.20.topo
certobs/obs2019-09-25/tip-az2019.09.25-14.40.topo
certobs/obs2019-09-25/tip-az2019.09.25-15.00.topo
certobs/obs2019-09-25/track-mars2019-09-25.topo
certobs/obs2019-11-05/2019-11-5   tip1.png
certobs/obs2019-11-05/2019-11-5   transitCasA.png
certobs/obs2019-11-05/2019-11-5   transitSgAS.png
certobs/obs2019-11-05/coords-2019.11.05-14.41.txt
certobs/obs2019-11-05/coords-2019.11.05-16.09.txt
certobs/obs2019-11-05/power1105.dat
certobs/obs2019-11-05/powerantitip1.dat
certobs/obs2019-11-05/powerantitip2.dat
certobs/obs2019-11-05/powerscanCasA.dat
certobs/obs2019-11-05/powerscanSgAS.dat
certobs/obs2019-11-05/powertip1.dat
certobs/obs2019-11-05/powertrackCasA.dat
certobs/obs2019-11-05/powertrackSgAS.dat
certobs/obs2019-11-05/powertransitCasA.dat
certobs/obs2019-11-05/powertransitSgAS.dat
certobs/obs2019-11-05/scan2019-11-5 _scanCasA.png
certobs/obs2019-11-05/tabla.fits
certobs/obs2019-11-05/pointings/CASN.topo
certobs-0.0.2.dist-info/LICENSE
certobs-0.0.2.dist-info/METADATA
certobs-0.0.2.dist-info/WHEEL
certobs-0.0.2.dist-info/top_level.txt
certobs-0.0.2.dist-info/RECORD
