Metadata-Version: 2.1
Name: certobs
Version: 0.0.2
Summary: Package for the planification of observing blocks for CERT (CESAR-ESA)
Home-page: https://github.com/pypa/sampleproject
Author: Diego Moral Pombo
Author-email: diegomoral94@gmail.com
License: UNKNOWN
Platform: UNKNOWN
Classifier: Programming Language :: Python :: 3
Classifier: License :: OSI Approved :: MIT License
Classifier: Operating System :: OS Independent
Requires-Python: >=3.6
